whyhow/__init__.py
whyhow/client.py
whyhow/exceptions.py
whyhow/schemas.py
whyhow/utils.py
whyhow/raw/__init__.py
whyhow/raw/autogen.py
whyhow/raw/base.py
whyhow/raw/chunks/__init__.py
whyhow/raw/chunks/requests.py
whyhow/raw/chunks/schemas.py
whyhow/raw/documents/__init__.py
whyhow/raw/documents/requests.py
whyhow/raw/documents/schemas.py
whyhow/raw/graphs/__init__.py
whyhow/raw/graphs/requests.py
whyhow/raw/graphs/schemas.py
whyhow/raw/nodes/__init__.py
whyhow/raw/nodes/requests.py
whyhow/raw/nodes/schemas.py
whyhow/raw/schemas/__init__.py
whyhow/raw/schemas/requests.py
whyhow/raw/schemas/schemas.py
whyhow/raw/tasks/__init__.py
whyhow/raw/tasks/requests.py
whyhow/raw/tasks/schemas.py
whyhow/raw/triples/__init__.py
whyhow/raw/triples/requests.py
whyhow/raw/triples/schemas.py
whyhow/raw/workspaces/__init__.py
whyhow/raw/workspaces/requests.py
whyhow/raw/workspaces/schemas.py
whyhow/resources/__init__.py
whyhow/resources/base.py
whyhow/resources/chunks.py
whyhow/resources/documents.py
whyhow/resources/graphs.py
whyhow/resources/nodes.py
whyhow/resources/schemas.py
whyhow/resources/triples.py
whyhow/resources/utils.py
whyhow/resources/workspaces.py
whyhow-0.1.12.dist-info/METADATA
whyhow-0.1.12.dist-info/WHEEL
whyhow-0.1.12.dist-info/top_level.txt
whyhow-0.1.12.dist-info/RECORD
