Metadata-Version: 2.1
Name: whyhow
Version: 0.1.12
Summary: Whyhow automated KG SDK
Author-email: Tom Smoker <tom@whyhow.ai>, Chris Rec <chris@whyhow.ai>
License: MIT
Project-URL: Homepage, https://github.com/whyhow-ai/whyhow
Keywords: SDK,KG
Classifier: Programming Language :: Python :: 3
Requires-Python: >=3.10
Requires-Dist: httpx
Requires-Dist: pydantic>1
Provides-Extra: dev
Requires-Dist: bandit[toml]; extra == "dev"
Requires-Dist: black; extra == "dev"
Requires-Dist: flake8; extra == "dev"
Requires-Dist: flake8-docstrings; extra == "dev"
Requires-Dist: fpdf; extra == "dev"
Requires-Dist: isort; extra == "dev"
Requires-Dist: mypy; extra == "dev"
Requires-Dist: pydocstyle[toml]; extra == "dev"
Requires-Dist: pytest-asyncio; extra == "dev"
Requires-Dist: pytest-cov; extra == "dev"
Requires-Dist: pytest-httpx; extra == "dev"
Requires-Dist: pytest; extra == "dev"
Requires-Dist: datamodel-code-generator; extra == "dev"
Provides-Extra: docs
Requires-Dist: mkdocs; extra == "docs"
Requires-Dist: mkdocstrings[python]; extra == "docs"
Requires-Dist: mkdocs-material; extra == "docs"
Requires-Dist: mkdocs-jupyter; extra == "docs"
Requires-Dist: pymdown-extensions; extra == "docs"
Requires-Dist: markdown-callouts; extra == "docs"
Requires-Dist: markdown-exec; extra == "docs"
